{
  "generated_at": "2026-06-29T10:15:15+00:00",
  "date": "2026-06-29",
  "games": [
    {
      "game_pk": 822792,
      "home_team_id": 141,
      "away_team_id": 121,
      "pre_home_win_prob": 0.5620499999999999,
      "pre_pred_home_runs": 4.894,
      "pre_pred_away_runs": 4.311
    },
    {
      "game_pk": 823121,
      "home_team_id": 136,
      "away_team_id": 108,
      "pre_home_win_prob": 0.571825,
      "pre_pred_home_runs": 4.387,
      "pre_pred_away_runs": 3.841
    },
    {
      "game_pk": 823444,
      "home_team_id": 143,
      "away_team_id": 134,
      "pre_home_win_prob": 0.4966,
      "pre_pred_home_runs": 4.932,
      "pre_pred_away_runs": 4.942
    },
    {
      "game_pk": 823529,
      "home_team_id": 147,
      "away_team_id": 116,
      "pre_home_win_prob": 0.5416500000000001,
      "pre_pred_home_runs": 4.39,
      "pre_pred_away_runs": 4.056
    },
    {
      "game_pk": 823771,
      "home_team_id": 158,
      "away_team_id": 113,
      "pre_home_win_prob": 0.62325,
      "pre_pred_home_runs": 5.293,
      "pre_pred_away_runs": 4.074
    },
    {
      "game_pk": 824176,
      "home_team_id": 117,
      "away_team_id": 142,
      "pre_home_win_prob": 0.531875,
      "pre_pred_home_runs": 4.797,
      "pre_pred_away_runs": 4.511
    },
    {
      "game_pk": 824339,
      "home_team_id": 115,
      "away_team_id": 146,
      "pre_home_win_prob": 0.429025,
      "pre_pred_home_runs": 5.076,
      "pre_pred_away_runs": 5.766
    },
    {
      "game_pk": 824420,
      "home_team_id": 114,
      "away_team_id": 140,
      "pre_home_win_prob": 0.5391,
      "pre_pred_home_runs": 3.894,
      "pre_pred_away_runs": 3.584
    },
    {
      "game_pk": 824662,
      "home_team_id": 112,
      "away_team_id": 135,
      "pre_home_win_prob": 0.559925,
      "pre_pred_home_runs": 4.749,
      "pre_pred_away_runs": 4.247
    },
    {
      "game_pk": 824741,
      "home_team_id": 111,
      "away_team_id": 120,
      "pre_home_win_prob": 0.619425,
      "pre_pred_home_runs": 5.046,
      "pre_pred_away_runs": 4.002
    },
    {
      "game_pk": 824822,
      "home_team_id": 110,
      "away_team_id": 145,
      "pre_home_win_prob": 0.5544,
      "pre_pred_home_runs": 5.268,
      "pre_pred_away_runs": 4.683
    },
    {
      "game_pk": 824986,
      "home_team_id": 133,
      "away_team_id": 119,
      "pre_home_win_prob": 0.482575,
      "pre_pred_home_runs": 4.524,
      "pre_pred_away_runs": 4.607
    },
    {
      "game_pk": 825065,
      "home_team_id": 109,
      "away_team_id": 137,
      "pre_home_win_prob": 0.5854250000000001,
      "pre_pred_home_runs": 4.573,
      "pre_pred_away_runs": 3.705
    }
  ],
  "pitcher_quality": {
    "663554": 0.0764,
    "663556": -0.0475,
    "663558": -0.0106,
    "663559": -0.211,
    "675848": 0.0353,
    "692230": -0.0015,
    "663562": 0.0001,
    "688138": -0.0002,
    "663567": 0.0426,
    "622608": 0.1034,
    "663568": 0.0872,
    "684049": -0.1412,
    "663574": -0.222,
    "688158": 0.0292,
    "593958": 0.1801,
    "806960": -0.3206,
    "593974": 0.008,
    "622663": 0.0213,
    "663623": -0.0622,
    "675911": -0.0303,
    "675916": 0.0643,
    "663629": -0.0,
    "667725": -0.0,
    "675921": -0.0001,
    "606303": -0.0622,
    "622694": 0.0001,
    "667755": -0.0093,
    "594027": 0.0996,
    "663687": 0.0064,
    "647315": 0.0507,
    "675989": -0.0704,
    "663704": 0.0001,
    "544931": -0.0002,
    "647336": 0.0513,
    "688297": -0.1777,
    "622766": 0.0001,
    "671922": 0.2815,
    "622772": 0.0001,
    "663734": -0.0,
    "647351": -0.0,
    "663738": 0.1111,
    "671936": 0.0464,
    "622786": -0.0,
    "696519": 0.048,
    "663752": 0.0002,
    "663753": 0.0001,
    "434378": -0.0042,
    "676050": 0.0,
    "676051": 0.0223,
    "663765": 0.0066,
    "663767": -0.0148,
    "643290": 0.0,
    "663773": 0.0001,
    "663776": -0.0,
    "663795": -0.0001,
    "676083": -0.0016,
    "598264": -0.0,
    "676092": -0.0001,
    "700669": -0.1115,
    "680192": 0.0,
    "676106": -0.0293,
    "684320": -0.1195,
    "676130": 0.0001,
    "680232": 0.0001,
    "700712": 0.0841,
    "663855": -0.0365,
    "643377": -0.0048,
    "663878": 0.025,
    "643410": 0.1221,
    "475479": 0.0001,
    "663903": -0.0712,
    "676194": 0.0,
    "528748": -0.0001,
    "663941": 0.0044,
    "663947": 0.0687,
    "676254": -0.0222,
    "663969": 0.0575,
    "643493": 0.0002,
    "676263": 0.0014,
    "676265": -0.0001,
    "663978": -0.1184,
    "676272": -0.0002,
    "643511": 0.1291,
    "663992": -0.0392,
    "676282": 0.0892,
    "455119": -0.0963,
    "664028": -0.0001,
    "434671": -0.0002,
    "664062": 0.0,
    "688642": -0.1404,
    "664074": -0.015,
    "664076": 0.0461,
    "672282": 0.0478,
    "643615": 0.0001,
    "676395": -0.0076,
    "623149": 0.014,
    "664123": 0.0001,
    "664126": -0.0877,
    "623167": -0.0,
    "664129": -0.0494,
    "676428": 0.0394,
    "664141": 0.0387,
    "672335": -0.069,
    "676440": -0.0612,
    "664161": 0.0002,
    "623211": 0.0458,
    "676467": -0.2404,
    "680570": -0.0927,
    "676477": 0.1047,
    "680573": -0.062,
    "664192": -0.0001,
    "664199": 0.0752,
    "672391": 0.0,
    "664208": -0.0795,
    "594577": 0.0,
    "594580": -0.0275,
    "676508": -0.0,
    "680604": -0.0637,
    "668338": -0.0001,
    "676534": 0.0997,
    "701121": 0.0841,
    "672456": 0.0271,
    "676568": -0.1438,
    "676571": 0.0046,
    "664285": -0.0193,
    "664294": -0.0,
    "668390": -0.0171,
    "664299": -0.1615,
    "680684": -0.0001,
    "680686": -0.0,
    "680689": -0.0096,
    "688883": -0.0413,
    "676596": 0.0,
    "606965": 0.0002,
    "680694": 0.0316,
    "623352": 0.102,
    "676601": 0.0001,
    "676604": 0.0143,
    "680702": 0.075,
    "680704": -0.0975,
    "676617": 0.1319,
    "664337": 0.0002,
    "680723": -0.0002,
    "606996": 0.1568,
    "680730": -0.1168,
    "680732": -0.0735,
    "664350": -0.0,
    "680735": 0.0001,
    "680736": 0.1508,
    "664353": -0.0056,
    "680739": 0.0001,
    "660261": -0.0001,
    "680742": 0.1416,
    "680744": 0.0985,
    "660271": 0.1389,
    "680755": 0.1035,
    "676664": -0.0192,
    "656186": -0.0001,
    "807743": -0.1479,
    "680767": -0.0784,
    "672578": 0.0001,
    "672582": -0.0707,
    "676684": 0.0851,
    "623437": -0.161,
    "656212": -0.0175,
    "607067": -0.1065,
    "623451": -0.0,
    "623454": 0.0638,
    "656222": -0.1214,
    "607074": 0.0462,
    "680802": -0.2529,
    "676710": 0.0001,
    "471911": -0.0144,
    "656232": -0.0,
    "656234": 0.0126,
    "676714": 0.0,
    "594798": 0.0853,
    "656240": 0.0,
    "676720": -0.0,
    "623474": 0.0854,
    "689017": 0.0,
    "676742": 0.0347,
    "656271": -0.0208,
    "594835": -0.0002,
    "676755": 0.0694,
    "676760": -0.056,
    "656288": -0.0028,
    "676775": 0.0975,
    "656302": 0.1268,
    "684974": -0.0671,
    "680880": 0.0,
    "680885": 0.0002,
    "680897": -0.0,
    "672710": -0.0,
    "541640": 0.0,
    "672715": 0.0002,
    "685005": -0.0659,
    "594902": 0.0002,
    "607192": 0.101,
    "607200": -0.0002,
    "656353": -0.0002,
    "656354": 0.0001,
    "680951": 0.0001,
    "668665": -0.0,
    "689147": 0.0554,
    "594943": 0.0001,
    "668674": -0.0628,
    "668676": -0.0001,
    "668678": -0.1233,
    "672782": -0.0407,
    "676879": 0.1425,
    "607259": 0.1385,
    "656412": 0.0002,
    "656420": 0.0,
    "500779": 0.015,
    "656427": -0.1088,
    "701487": -0.0002,
    "685107": 0.0002,
    "676917": -0.0132,
    "685116": -0.0001,
    "693312": -0.1456,
    "693313": 0.0,
    "685126": -0.0029,
    "595014": 0.0601,
    "656457": -0.0087,
    "689225": -0.0001,
    "681035": 0.1079,
    "701519": -0.0172,
    "656464": 0.0599,
    "672851": 0.0001,
    "676961": -0.0001,
    "676962": 0.1971,
    "689254": 0.0713,
    "701542": -0.1018,
    "681066": -0.0001,
    "656492": 0.0871,
    "676974": 0.1196,
    "701552": -0.1573,
    "660593": -0.0,
    "689266": -0.0015,
    "676979": 0.0448,
    "660604": 0.0869,
    "701581": 0.0001,
    "660623": 0.0,
    "689296": 0.0032,
    "656529": 0.0295,
    "656546": 0.2074,
    "668834": -0.0001,
    "656550": 0.0671,
    "656557": -0.0002,
    "693433": -0.0032,
    "677053": -0.0369,
    "681151": -0.0919,
    "656578": -0.0001,
    "668868": -0.0001,
    "668873": -0.0138,
    "668874": -0.0001,
    "681168": -0.1474,
    "668881": -0.0,
    "701656": 0.0567,
    "656605": -0.0124,
    "607455": 0.0458,
    "681190": 0.0636,
    "668909": 0.0312,
    "685299": 0.0029,
    "656629": -0.0003,
    "595191": -0.0002,
    "607481": -0.2557,
    "660730": 0.0001,
    "656638": 0.0606,
    "656641": 0.1645,
    "681217": 0.0284,
    "668933": 0.0554,
    "570632": 0.0001,
    "668941": 0.0089,
    "685326": 0.0001,
    "656657": -0.0002,
    "615698": -0.0066,
    "668948": -0.0001,
    "664854": -0.041,
    "701719": 0.065,
    "660761": 0.0962,
    "689441": -0.0265,
    "668964": -0.1289,
    "681252": 0.0023,
    "677161": 0.0397,
    "570666": -0.0001,
    "664875": -0.2135,
    "656685": 0.0,
    "656686": -0.1397,
    "607536": -0.1246,
    "800048": 0.0868,
    "800049": 0.0001,
    "660787": -0.0241,
    "668984": 0.1117,
    "660813": 0.0,
    "681293": 0.0227,
    "660825": 0.1256,
    "656730": 0.3303,
    "656731": 0.0001,
    "669020": 0.0017,
    "669022": 0.0046,
    "685410": -0.0,
    "689520": -0.0379,
    "656756": -0.0002,
    "660853": 0.0759,
    "681343": -0.0492,
    "681347": -0.0367,
    "669060": -0.0002,
    "669062": -0.0197,
    "607625": -0.0596,
    "689546": 0.0033,
    "693645": 0.1859,
    "595345": 0.0654,
    "656793": -0.0,
    "656794": 0.2636,
    "607644": 0.0,
    "669084": 0.0268,
    "664991": 0.2982,
    "669093": 0.037,
    "665001": 0.0002,
    "660906": 0.0,
    "804267": 0.0367,
    "656818": 0.0,
    "693686": 0.1328,
    "681402": -0.1055,
    "640444": -0.0,
    "554430": 0.2495,
    "685503": 0.0001,
    "640448": -0.0259,
    "640455": 0.0906,
    "640462": -0.0001,
    "656848": 0.1866,
    "656849": -0.0288,
    "697812": 0.003,
    "681432": -0.0001,
    "669145": -0.0001,
    "669160": -0.0027,
    "656876": 0.0509,
    "669165": 0.0968,
    "669169": 0.0,
    "624133": 0.0563,
    "689672": -0.0001,
    "669194": -0.0821,
    "669199": 0.062,
    "669203": -0.0001,
    "669211": -0.0301,
    "669212": -0.1169,
    "472610": -0.0751,
    "681517": -0.0169,
    "656945": 0.177,
    "800311": 0.2036,
    "656954": 0.0,
    "693821": -0.0295,
    "665152": -0.071,
    "702021": 0.0073,
    "656970": 0.0001,
    "669270": -0.1149,
    "669276": 0.3455,
    "628317": -0.0002,
    "693855": -0.0011,
    "702056": 0.0241,
    "837227": 0.0383,
    "657006": -0.0,
    "669302": 0.1239,
    "702070": -0.0281,
    "669308": 0.0001,
    "820862": 0.0054,
    "657024": -0.0002,
    "501381": -0.0,
    "657031": 0.0002,
    "669330": 0.0734,
    "657044": 0.0515,
    "689818": -0.0919,
    "657053": 0.0,
    "489119": -0.0001,
    "669358": 0.0339,
    "448179": -0.0002,
    "669371": -0.0869,
    "669372": 0.145,
    "669373": 0.1703,
    "657093": 0.0,
    "657097": 0.0121,
    "702153": 0.0375,
    "669387": 0.1046,
    "681676": 0.0747,
    "669395": 0.0001,
    "607968": -0.0001,
    "628452": 0.2045,
    "685801": -0.0354,
    "673513": -0.0023,
    "669422": 0.0001,
    "669424": 0.0001,
    "702193": 0.1671,
    "657140": 0.0001,
    "669432": -0.0355,
    "669438": -0.0314,
    "579328": -0.0613,
    "673540": -0.0507,
    "669456": -0.1922,
    "669459": 0.0,
    "677651": 0.0001,
    "661269": -0.0001,
    "669461": -0.1436,
    "694037": 0.0409,
    "681751": -0.0651,
    "669467": 0.0499,
    "804636": -0.0496,
    "689958": 0.0001,
    "624431": 0.0195,
    "456501": -0.0,
    "661309": -0.0001,
    "689981": -0.0001,
    "702273": -0.1039,
    "702275": -0.0923,
    "681799": -0.0804,
    "702281": -0.0829,
    "681806": 0.0001,
    "681810": 0.0117,
    "657240": 0.0001,
    "829272": 0.0001,
    "702303": 0.0441,
    "657248": -0.0002,
    "489334": 0.0001,
    "657277": 0.108,
    "681857": -0.0001,
    "624522": 0.0671,
    "681867": 0.0398,
    "681869": 0.0001,
    "681870": 0.211,
    "702352": 0.0,
    "661395": 0.3428,
    "681882": 0.0,
    "681885": -0.0001,
    "681892": -0.133,
    "681895": 0.1792,
    "595881": -0.0,
    "669620": -0.0001,
    "669622": 0.2334,
    "681911": 0.2185,
    "681916": 0.0152,
    "661440": 0.0002,
    "477132": 0.0002,
    "657376": 0.0001,
    "595939": -0.0,
    "489446": 0.0838,
    "628711": 0.0001,
    "677865": 0.0654,
    "669674": 0.0002,
    "690155": 0.0336,
    "669684": 0.0262,
    "681982": -0.067,
    "808963": -0.0986,
    "808967": 0.2039,
    "456713": -0.0001,
    "702474": -0.1018,
    "669711": -0.0214,
    "657424": -0.1466,
    "669713": 0.0001,
    "665621": -0.0,
    "665622": 0.0425,
    "665625": 0.0001,
    "669721": 0.0001,
    "694297": -0.1276,
    "669724": -0.0572,
    "596001": 0.1371,
    "677944": 0.0226,
    "661563": -0.2631,
    "665660": -0.0419,
    "694335": -0.0657,
    "677952": -0.0066,
    "665665": 0.0001,
    "682051": 0.0,
    "682052": -0.1395,
    "677955": 0.0138,
    "677958": -0.1009,
    "677960": 0.0076,
    "677961": -0.0289,
    "694346": -0.1094,
    "596043": 0.0001,
    "608331": 0.0053,
    "608334": 0.0001,
    "608337": 0.049,
    "571479": 0.0,
    "608344": 0.0,
    "596057": 0.0,
    "694361": 0.1137,
    "694363": 0.0108,
    "694360": -0.082,
    "677985": 0.0001,
    "657508": -0.0001,
    "596071": -0.0001,
    "657514": 0.0834,
    "608371": -0.0221,
    "608372": 0.1495,
    "571510": 0.0212,
    "608379": 0.132,
    "641149": -0.0002,
    "641154": 0.0001,
    "678020": -0.117,
    "678022": -0.0109,
    "678024": 0.0,
    "673929": -0.18,
    "686218": -0.1296,
    "682120": -0.0712,
    "645261": -0.0142,
    "669854": -0.0001,
    "542881": 0.0001,
    "657571": 0.0614,
    "596133": 0.202,
    "542888": -0.0035,
    "678061": 0.0,
    "657585": 0.0001,
    "547001": -0.0002,
    "571578": -0.0013,
    "682171": -0.0,
    "694462": 0.0001,
    "682175": -0.0,
    "665795": -0.0967,
    "657612": 0.0032,
    "694477": 0.0812,
    "702674": -0.0002,
    "674003": 0.0001,
    "592094": -0.0577,
    "571616": -0.0,
    "501985": -0.0001,
    "669920": -0.1189,
    "542947": 0.0001,
    "669923": 0.0061,
    "657649": -0.0001,
    "682227": -0.0269,
    "669947": -0.1209,
    "518397": -0.0,
    "669952": 0.0,
    "682243": 0.0664,
    "805123": -0.0051,
    "571656": 0.0001,
    "682254": 0.0705,
    "665871": 0.0274,
    "641302": 0.101,
    "674072": -0.0,
    "502042": -0.0001,
    "502043": -0.0001,
    "592155": 0.0328,
    "641312": -0.0941,
    "702752": -0.0554,
    "813349": 0.1354,
    "641329": 0.1454,
    "608566": -0.0511,
    "543037": 0.0716,
    "596295": -0.0001,
    "543056": -0.0132,
    "657746": 0.0566,
    "670036": -0.0128,
    "518489": -0.0003,
    "657756": 0.0334,
    "670046": 0.0001,
    "592229": 0.0,
    "547179": -0.0141,
    "670059": 0.1895,
    "571760": -0.0002,
    "547184": -0.0731,
    "801139": -0.0136,
    "518516": -0.0001,
    "694646": -0.0001,
    "641401": -0.1279,
    "543101": 0.0001,
    "592254": -0.0001,
    "608638": 0.0,
    "608650": 0.0342,
    "608652": -0.0002,
    "670102": -0.0001,
    "571800": -0.0001,
    "694680": -0.1827,
    "502171": -0.0001,
    "543135": 0.0798,
    "502179": -0.0001,
    "641447": -0.0001,
    "670124": -0.0001,
    "805299": 0.1782,
    "518585": 0.1302,
    "641482": 0.0,
    "592332": 0.0203,
    "608717": -0.0,
    "608718": 0.0577,
    "682445": -0.0528,
    "694738": -0.1033,
    "608723": -0.1811,
    "571863": 0.0,
    "621016": 0.0001,
    "670167": -0.0971,
    "592346": 0.0001,
    "670174": 0.0,
    "592351": 0.0001,
    "678368": -0.2486,
    "686560": -0.0376,
    "686563": -0.0,
    "670183": 0.0808,
    "571882": 0.0002,
    "686580": -0.0159,
    "678394": -0.181,
    "621051": -0.0001,
    "621053": -0.0884,
    "621057": 0.0002,
    "641540": 0.0,
    "666120": -0.0001,
    "543243": 0.1356,
    "694795": -0.0002,
    "666129": -0.0321,
    "686610": -0.1977,
    "621074": -0.0073,
    "621076": -0.0,
    "686613": 0.1055,
    "571927": -0.0777,
    "694813": -0.0,
    "666142": 0.0112,
    "670241": 0.0002,
    "694819": 0.1825,
    "670245": -0.082,
    "571945": -0.0502,
    "571946": 0.0001,
    "621097": -0.0716,
    "571948": -0.0303,
    "666154": -0.0,
    "641582": 0.0,
    "666157": -0.0264,
    "666159": 0.0002,
    "641585": -0.068,
    "686642": -0.0,
    "621107": -0.0037,
    "805427": 0.093,
    "621111": 0.0833,
    "621112": 0.0489,
    "621114": 0.0,
    "666171": 0.0394,
    "686651": 0.0001,
    "543294": 0.0002,
    "506433": 0.0,
    "621121": -0.1866,
    "674370": -0.1135,
    "694851": -0.1219,
    "592454": -0.051,
    "670280": 0.1654,
    "666200": 0.0123,
    "666201": -0.0966,
    "666204": -0.0,
    "666205": -0.0001,
    "678495": 0.0,
    "666214": -0.0004,
    "686701": 0.0001,
    "682608": 0.1126,
    "682610": -0.0,
    "572020": -0.0,
    "641656": 0.0001,
    "670329": 0.0325,
    "801403": 0.0085,
    "694918": 0.0429,
    "641672": -0.0,
    "686730": 0.0,
    "674444": -0.1809,
    "690829": 0.0,
    "621199": -0.0001,
    "801434": 0.0469,
    "686751": -0.0092,
    "686752": -0.0001,
    "686753": -0.0253,
    "621219": 0.0,
    "666277": -0.0117,
    "453286": -0.139,
    "572070": -0.0002,
    "641703": -0.0002,
    "641712": -0.0,
    "621237": 0.121,
    "621242": -0.0124,
    "621244": -0.0003,
    "694973": -0.0182,
    "641726": -0.0002,
    "621249": -0.0001,
    "686790": 0.0191,
    "527048": 0.1389,
    "686796": -0.0,
    "527054": 0.0001,
    "641743": 0.0127,
    "686799": -0.1524,
    "641745": 0.0077,
    "678606": 0.138,
    "695001": 0.0596,
    "641755": -0.0136,
    "518876": -0.0647,
    "690916": -0.0001,
    "518886": -0.0651,
    "686826": -0.0001,
    "641771": -0.0001,
    "662253": 0.1023,
    "690925": -0.0014,
    "572143": 0.0376,
    "690928": -0.024,
    "641778": 0.0394,
    "543475": 0.0,
    "686839": -0.0001,
    "695034": -0.0188,
    "699134": 0.1631,
    "641793": -0.0257,
    "666374": 0.1229,
    "690953": 0.1484,
    "592662": 0.0909,
    "641816": 0.0213,
    "543518": 0.0,
    "543521": -0.0001,
    "621345": 0.1395,
    "690978": 0.0494,
    "678692": -0.0,
    "695076": -0.0601,
    "805673": 0.014,
    "690986": 0.0975,
    "641835": 0.1087,
    "690990": -0.0207,
    "690997": 0.0541,
    "621366": -0.0509,
    "621368": 0.0001,
    "543548": -0.0002,
    "691008": -0.0593,
    "621381": -0.2264,
    "621383": 0.035,
    "682825": -0.093,
    "592716": -0.0002,
    "592717": -0.0002,
    "621389": 0.0,
    "691021": 0.0002,
    "686930": 0.0819,
    "682842": 0.0749,
    "445276": -0.0787,
    "682847": 0.0001,
    "502624": -0.0,
    "543606": 0.0001,
    "592761": -0.0001,
    "674681": -0.0001,
    "686973": 0.3968,
    "592767": -0.0001,
    "592773": -0.0932,
    "641927": -0.0745,
    "686993": -0.0592,
    "592789": -0.0002,
    "641941": -0.0924,
    "592791": 0.0958,
    "699315": 0.0001,
    "814005": -0.0,
    "592826": 0.0001,
    "592836": -0.2709,
    "695239": -0.0174,
    "605130": -0.1751,
    "695243": 0.4,
    "605135": -0.0872,
    "687064": 0.1116,
    "592866": -0.0,
    "605154": 0.0,
    "605156": -0.0002,
    "519141": -0.1635,
    "687075": -0.0191,
    "625643": 0.0375,
    "605164": -0.0,
    "642028": 0.0,
    "682989": -0.0003,
    "682990": 0.0003,
    "682995": -0.1658,
    "683000": -0.0539,
    "678906": -0.0466,
    "683003": -0.1128,
    "523260": -0.0001,
    "683004": -0.0903,
    "605182": 0.0001,
    "666619": -0.0123,
    "605200": 0.0,
    "543766": -0.0,
    "674841": 0.0731,
    "687134": -0.0003,
    "605218": 0.0135,
    "666661": 0.1674,
    "670766": 0.0001,
    "642100": 0.1095,
    "605242": -0.0001,
    "642121": 0.0374,
    "519242": 0.2486,
    "695380": 0.1241,
    "666711": 0.0405,
    "605280": 0.1604,
    "666720": -0.0003,
    "646242": -0.0002,
    "666721": -0.0003,
    "646241": 0.1407,
    "547943": 0.0001,
    "605288": -0.0232,
    "642152": -0.0,
    "687209": -0.1811,
    "687223": 0.0007,
    "666745": 0.0,
    "695418": 0.0534,
    "703615": -0.0405,
    "674944": -0.0,
    "547973": 0.2079,
    "683155": -0.0038,
    "605335": -0.1144,
    "642207": 0.1259,
    "683175": -0.1355,
    "642216": -0.0001,
    "642231": 0.0001,
    "642232": 0.0878,
    "666808": 0.0019,
    "642239": 0.0001,
    "670912": 0.0001,
    "695505": 0.2312,
    "605397": 0.0001,
    "605400": -0.0592,
    "658648": -0.0,
    "683227": 0.0001,
    "683232": -0.0431,
    "687330": 0.0708,
    "670950": -0.0886,
    "695534": -0.0772,
    "691441": -0.0002,
    "679156": 0.0001,
    "670970": 0.3034,
    "695549": 0.0004,
    "687362": -0.0,
    "630023": 0.0002,
    "605447": 0.0023,
    "605452": -0.1381,
    "670990": 0.0449,
    "687377": 0.0066,
    "605463": -0.0,
    "650530": 0.0001,
    "687396": 0.1504,
    "806185": -0.0,
    "605483": 0.0007,
    "806188": 0.034,
    "605488": -0.2189,
    "695611": 0.1918,
    "650556": -0.1928,
    "687424": -0.0,
    "605507": -0.0001,
    "605513": -0.0,
    "683352": 0.0001,
    "642397": 0.0939,
    "666974": 0.1745,
    "605538": 0.0,
    "605540": 0.0575,
    "687473": 0.0292,
    "671096": 0.0666,
    "671106": -0.0001,
    "691587": -0.0041,
    "695684": -0.0416,
    "671111": -0.0102,
    "650633": 0.0717,
    "650644": -0.0006,
    "544150": -0.1262,
    "671131": 0.0,
    "687531": 0.1152,
    "699823": -0.0122,
    "593334": -0.0001,
    "679358": 0.1024,
    "687562": 0.0269,
    "687570": -0.1561,
    "642520": -0.0001,
    "642528": 0.1068,
    "445926": -0.0001,
    "671212": 0.069,
    "622065": -0.0001,
    "642545": -0.0001,
    "642547": 0.0217,
    "642546": -0.1626,
    "687606": -0.0247,
    "622072": 0.0001,
    "622088": 0.0763,
    "691725": -0.1414,
    "593423": 0.0,
    "572955": -0.0809,
    "548384": 0.0961,
    "548389": 0.0,
    "572971": -0.0001,
    "691769": -0.1168,
    "573009": 0.1019,
    "691799": 0.2803,
    "683618": 0.1806,
    "679525": 0.0001,
    "683627": -0.0381,
    "601713": 0.2119,
    "802419": -0.0,
    "663158": 0.184,
    "642701": -0.0531,
    "687765": -0.1977,
    "671382": -0.0503,
    "503449": 0.0001,
    "450203": -0.0001,
    "650911": 0.2043,
    "667297": 0.0614,
    "622250": 0.0002,
    "622251": -0.0001,
    "687792": 0.0001,
    "687798": -0.0001,
    "675512": 0.1373,
    "552640": -0.0561,
    "573124": 0.0087,
    "650960": 0.0414,
    "642770": -0.0001,
    "675540": 0.0001,
    "687830": -0.0003,
    "683742": -0.1535,
    "802528": -0.0,
    "687849": -0.1301,
    "691946": -0.0143,
    "691945": -0.0691,
    "691951": 0.008,
    "683769": -0.0035,
    "696062": 0.0085,
    "573186": 0.0001,
    "696070": 0.053,
    "687888": -0.0,
    "642834": 0.0001,
    "573204": -0.0864,
    "614179": -0.0001,
    "687911": 0.1075,
    "622379": -0.0,
    "675627": 0.0,
    "687922": -0.0003,
    "687924": -0.0001,
    "687931": 0.0142,
    "425794": -0.0002,
    "663362": -0.0734,
    "675650": 0.0,
    "696131": -0.1003,
    "667463": 0.0868,
    "696136": 0.0098,
    "659275": 0.0001,
    "663372": 0.0168,
    "675660": -0.0468,
    "700241": 0.0518,
    "663378": 0.0001,
    "696147": -0.0329,
    "696149": -0.0153,
    "700249": -0.1172,
    "679775": 0.0054,
    "663399": -0.0002,
    "667498": -0.0001,
    "700270": -0.0001,
    "425844": 0.0001,
    "663423": -0.1427,
    "663436": 0.159,
    "622491": -0.0536,
    "663455": -0.0001,
    "446372": 0.0001,
    "663460": 0.1087,
    "622503": -0.0,
    "663465": -0.0427,
    "663474": 0.0003,
    "458681": -0.0,
    "663485": -0.0234,
    "679883": 0.0508,
    "700363": 0.0001,
    "696270": -0.1626,
    "622554": -0.0693,
    "684007": -0.0249,
    "688107": -0.0389,
    "815083": -0.1099,
    "663542": 0.0222,
    "671737": -0.0551,
    "663546": 0.0001
  }
}
