{
  "updated_at": "2026-07-17T02:47:14+00:00",
  "date": "2026-07-17",
  "live_game_count": 0,
  "games": [
    {
      "game_pk": 823440,
      "home_team_id": 143,
      "away_team_id": 121,
      "abstract_status": "Final",
      "detailed_status": "Final",
      "pre_home_win_prob": 0.41245000000000004,
      "live_home_win_prob": null,
      "linescore": null,
      "lineups": {
        "home": [
          {
            "order": 1,
            "player_id": 607208,
            "name": "Trea Turner",
            "season_avg": ".236",
            "season_obp": ".284",
            "season_slg": ".362"
          },
          {
            "order": 2,
            "player_id": 656941,
            "name": "Kyle Schwarber",
            "season_avg": ".254",
            "season_obp": ".366",
            "season_slg": ".559"
          },
          {
            "order": 3,
            "player_id": 547180,
            "name": "Bryce Harper",
            "season_avg": ".261",
            "season_obp": ".367",
            "season_slg": ".499"
          },
          {
            "order": 4,
            "player_id": 669016,
            "name": "Brandon Marsh",
            "season_avg": ".297",
            "season_obp": ".335",
            "season_slg": ".484"
          },
          {
            "order": 5,
            "player_id": 664761,
            "name": "Alec Bohm",
            "season_avg": ".213",
            "season_obp": ".275",
            "season_slg": ".350"
          },
          {
            "order": 6,
            "player_id": 681082,
            "name": "Bryson Stott",
            "season_avg": ".247",
            "season_obp": ".305",
            "season_slg": ".389"
          },
          {
            "order": 7,
            "player_id": 592663,
            "name": "J.T. Realmuto",
            "season_avg": ".208",
            "season_obp": ".288",
            "season_slg": ".346"
          },
          {
            "order": 8,
            "player_id": 687282,
            "name": "Gabriel Rincones Jr.",
            "season_avg": ".171",
            "season_obp": ".203",
            "season_slg": ".300"
          },
          {
            "order": 9,
            "player_id": 702222,
            "name": "Justin Crawford",
            "season_avg": ".260",
            "season_obp": ".309",
            "season_slg": ".349"
          }
        ],
        "away": [
          {
            "order": 1,
            "player_id": 805999,
            "name": "A.J. Ewing",
            "season_avg": ".274",
            "season_obp": ".347",
            "season_slg": ".438"
          },
          {
            "order": 2,
            "player_id": 621438,
            "name": "Tyrone Taylor",
            "season_avg": ".215",
            "season_obp": ".246",
            "season_slg": ".413"
          },
          {
            "order": 3,
            "player_id": 666182,
            "name": "Bo Bichette",
            "season_avg": ".253",
            "season_obp": ".297",
            "season_slg": ".372"
          },
          {
            "order": 4,
            "player_id": 596019,
            "name": "Francisco Lindor",
            "season_avg": ".210",
            "season_obp": ".291",
            "season_slg": ".363"
          },
          {
            "order": 5,
            "player_id": 701807,
            "name": "Carson Benge",
            "season_avg": ".263",
            "season_obp": ".326",
            "season_slg": ".401"
          },
          {
            "order": 6,
            "player_id": 593871,
            "name": "Jorge Polanco",
            "season_avg": ".169",
            "season_obp": ".229",
            "season_slg": ".260"
          },
          {
            "order": 7,
            "player_id": 676724,
            "name": "Jared Young",
            "season_avg": ".245",
            "season_obp": ".323",
            "season_slg": ".420"
          },
          {
            "order": 8,
            "player_id": 683146,
            "name": "Brett Baty",
            "season_avg": ".224",
            "season_obp": ".299",
            "season_slg": ".327"
          },
          {
            "order": 9,
            "player_id": 682626,
            "name": "Francisco Alvarez",
            "season_avg": ".259",
            "season_obp": ".325",
            "season_slg": ".448"
          }
        ]
      },
      "starting_pitchers": null
    },
    {
      "game_pk": 824766,
      "home_team_id": 111,
      "away_team_id": 139,
      "abstract_status": "Preview",
      "detailed_status": "Scheduled",
      "pre_home_win_prob": null,
      "live_home_win_prob": null,
      "linescore": null,
      "lineups": {
        "home": null,
        "away": null
      },
      "starting_pitchers": null
    },
    {
      "game_pk": 824737,
      "home_team_id": 111,
      "away_team_id": 139,
      "abstract_status": "Preview",
      "detailed_status": "Scheduled",
      "pre_home_win_prob": null,
      "live_home_win_prob": null,
      "linescore": null,
      "lineups": {
        "home": null,
        "away": null
      },
      "starting_pitchers": null
    },
    {
      "game_pk": 823524,
      "home_team_id": 147,
      "away_team_id": 119,
      "abstract_status": "Preview",
      "detailed_status": "Scheduled",
      "pre_home_win_prob": null,
      "live_home_win_prob": null,
      "linescore": null,
      "lineups": {
        "home": null,
        "away": null
      },
      "starting_pitchers": null
    },
    {
      "game_pk": 824414,
      "home_team_id": 114,
      "away_team_id": 134,
      "abstract_status": "Preview",
      "detailed_status": "Scheduled",
      "pre_home_win_prob": null,
      "live_home_win_prob": null,
      "linescore": null,
      "lineups": {
        "home": null,
        "away": null
      },
      "starting_pitchers": null
    },
    {
      "game_pk": 824901,
      "home_team_id": 144,
      "away_team_id": 140,
      "abstract_status": "Preview",
      "detailed_status": "Scheduled",
      "pre_home_win_prob": null,
      "live_home_win_prob": null,
      "linescore": null,
      "lineups": {
        "home": null,
        "away": null
      },
      "starting_pitchers": null
    },
    {
      "game_pk": 822789,
      "home_team_id": 141,
      "away_team_id": 145,
      "abstract_status": "Preview",
      "detailed_status": "Scheduled",
      "pre_home_win_prob": null,
      "live_home_win_prob": null,
      "linescore": null,
      "lineups": {
        "home": null,
        "away": null
      },
      "starting_pitchers": null
    },
    {
      "game_pk": 823766,
      "home_team_id": 158,
      "away_team_id": 146,
      "abstract_status": "Preview",
      "detailed_status": "Scheduled",
      "pre_home_win_prob": null,
      "live_home_win_prob": null,
      "linescore": null,
      "lineups": {
        "home": null,
        "away": null
      },
      "starting_pitchers": null
    },
    {
      "game_pk": 824655,
      "home_team_id": 112,
      "away_team_id": 142,
      "abstract_status": "Preview",
      "detailed_status": "Scheduled",
      "pre_home_win_prob": null,
      "live_home_win_prob": null,
      "linescore": null,
      "lineups": {
        "home": null,
        "away": null
      },
      "starting_pitchers": null
    },
    {
      "game_pk": 824170,
      "home_team_id": 117,
      "away_team_id": 110,
      "abstract_status": "Preview",
      "detailed_status": "Scheduled",
      "pre_home_win_prob": null,
      "live_home_win_prob": null,
      "linescore": null,
      "lineups": {
        "home": null,
        "away": null
      },
      "starting_pitchers": null
    },
    {
      "game_pk": 824090,
      "home_team_id": 118,
      "away_team_id": 135,
      "abstract_status": "Preview",
      "detailed_status": "Scheduled",
      "pre_home_win_prob": null,
      "live_home_win_prob": null,
      "linescore": null,
      "lineups": {
        "home": null,
        "away": null
      },
      "starting_pitchers": null
    },
    {
      "game_pk": 824332,
      "home_team_id": 115,
      "away_team_id": 113,
      "abstract_status": "Preview",
      "detailed_status": "Scheduled",
      "pre_home_win_prob": null,
      "live_home_win_prob": null,
      "linescore": null,
      "lineups": {
        "home": null,
        "away": null
      },
      "starting_pitchers": null
    },
    {
      "game_pk": 824009,
      "home_team_id": 108,
      "away_team_id": 116,
      "abstract_status": "Preview",
      "detailed_status": "Scheduled",
      "pre_home_win_prob": null,
      "live_home_win_prob": null,
      "linescore": null,
      "lineups": {
        "home": null,
        "away": null
      },
      "starting_pitchers": null
    },
    {
      "game_pk": 824981,
      "home_team_id": 133,
      "away_team_id": 120,
      "abstract_status": "Preview",
      "detailed_status": "Scheduled",
      "pre_home_win_prob": null,
      "live_home_win_prob": null,
      "linescore": null,
      "lineups": {
        "home": null,
        "away": null
      },
      "starting_pitchers": null
    },
    {
      "game_pk": 825060,
      "home_team_id": 109,
      "away_team_id": 138,
      "abstract_status": "Preview",
      "detailed_status": "Scheduled",
      "pre_home_win_prob": null,
      "live_home_win_prob": null,
      "linescore": null,
      "lineups": {
        "home": null,
        "away": null
      },
      "starting_pitchers": null
    },
    {
      "game_pk": 823115,
      "home_team_id": 136,
      "away_team_id": 137,
      "abstract_status": "Preview",
      "detailed_status": "Scheduled",
      "pre_home_win_prob": null,
      "live_home_win_prob": null,
      "linescore": null,
      "lineups": {
        "home": null,
        "away": null
      },
      "starting_pitchers": null
    }
  ]
}
